sc2_tournament_analysis/__init__.py
sc2_tournament_analysis/defaults.py
sc2_tournament_analysis/handle_replay.py
sc2_tournament_analysis/json_to_csv.py
sc2_tournament_analysis/recursive_parse.py
sc2_tournament_analysis/regex.py
sc2_tournament_analysis-0.0.18.dist-info/LICENSE
sc2_tournament_analysis-0.0.18.dist-info/METADATA
sc2_tournament_analysis-0.0.18.dist-info/WHEEL
sc2_tournament_analysis-0.0.18.dist-info/top_level.txt
sc2_tournament_analysis-0.0.18.dist-info/RECORD
