Metadata-Version: 2.1
Name: sc2-tournament-analysis
Version: 0.0.18
Summary: A script for analyzing tournament replay packs
Home-page: https://github.com/ZephyrBlu/sc2-tournament-analysis
Author: ZephyrBlu/Luke Holroyd
Author-email: hello@zephyrus.gg
License: UNKNOWN
Platform: UNKNOWN
Classifier: Programming Language :: Python :: 3
Classifier: License :: OSI Approved :: MIT License
Classifier: Operating System :: OS Independent
Requires-Python: >=3.6
